fashionable/__init__.py
fashionable/attribute.py
fashionable/baseattribute.py
fashionable/cistr.py
fashionable/errors.py
fashionable/model.py
fashionable/modelmeta.py
fashionable/supermodel.py
fashionable/typedef.py
fashionable/unset.py
fashionable/validation.py
fashionable/decorator/__init__.py
fashionable/decorator/arg.py
fashionable/decorator/fashionable_.py
fashionable/decorator/func.py
fashionable-0.12.3.dist-info/LICENSE
fashionable-0.12.3.dist-info/METADATA
fashionable-0.12.3.dist-info/WHEEL
fashionable-0.12.3.dist-info/top_level.txt
fashionable-0.12.3.dist-info/RECORD
