Metadata-Version: 2.1
Name: fashionable
Version: 0.12.3
Summary: Decorate your project with some fashionable supermodels
Home-page: https://github.com/mon4ter/fashionable
Author: Dmitry Galkin
Author-email: mon4ter@gmail.com
License: MIT
Platform: UNKNOWN
Classifier: Development Status :: 4 - Beta
Classifier: Programming Language :: Python :: 3.5
Classifier: Programming Language :: Python :: 3.6
Classifier: Programming Language :: Python :: 3.7
Classifier: Programming Language :: Python :: 3.8
Classifier: Programming Language :: Python :: 3.9
Classifier: Programming Language :: Python :: 3.10
Classifier: License :: OSI Approved :: MIT License
Classifier: Operating System :: OS Independent
License-File: LICENSE
